dice_lib/__init__.py
dice_lib/_config.py
dice_lib/date.py
dice_lib/glossary.py
dice_lib/host.py
dice_lib/logger.py
dice_lib/py.typed
dice_lib/ranges.py
dice_lib/units.py
dice_lib/user.py
dice_lib/distributed/__init__.py
dice_lib/fs/__init__.py
dice_lib/fs/_base.py
dice_lib/fs/_davix.py
dice_lib/fs/_gridftp.py
dice_lib/fs/_hdfs.py
dice_lib/fs/_posix.py
dice_lib/fs/_s3.py
dice_lib/fs/_xrootd.py
dice_lib/health/__init__.py
dice_lib/health/apel_accounting.py
dice_lib/network/__init__.py
dice_lib-2025.3.1.dist-info/METADATA
dice_lib-2025.3.1.dist-info/WHEEL
dice_lib-2025.3.1.dist-info/licenses/LICENSE
dice_lib-2025.3.1.dist-info/RECORD
