Metadata-Version: 2.4
Name: dice_lib
Version: 2025.3.1
Summary: Python Library for DICE
Project-URL: homepage, https://github.com/uobdic/dice-lib
Project-URL: Bug Tracker, https://github.com/uobdic/dice-lib/issues
Project-URL: Discussions, https://github.com/uobdic/dice-lib/discussions
Project-URL: Changelog, https://github.com/uobdic/dice-lib/releases
Author-email: UoB DICE team <lcg-admin@bristol.ac.uk>
Maintainer-email: The UoB DICE Team <lcg-admin@bristol.ac.uk>
License: BSD 3-Clause License
License-File: LICENSE
Classifier: Development Status :: 4 - Beta
Classifier: Intended Audience :: Developers
Classifier: Intended Audience :: Science/Research
Classifier: License :: OSI Approved :: BSD License
Classifier: Operating System :: OS Independent
Classifier: Programming Language :: Python
Classifier: Programming Language :: Python :: 3
Classifier: Programming Language :: Python :: 3.9
Classifier: Programming Language :: Python :: 3.10
Classifier: Programming Language :: Python :: 3.11
Classifier: Topic :: Scientific/Engineering
Requires-Python: >=3.6
Requires-Dist: beautifulsoup4<5
Requires-Dist: dnspython>=2.2.0
Requires-Dist: fasthep-logging
Requires-Dist: htcondor>=23
Requires-Dist: omegaconf>=2.1.2
Requires-Dist: pandas
Requires-Dist: paramiko
Requires-Dist: plumbum
Requires-Dist: pyarrow
Requires-Dist: pydantic
Requires-Dist: pyhdfs
Requires-Dist: python-nmap
Provides-Extra: dev
Requires-Dist: pytest-cov>=3; extra == 'dev'
Requires-Dist: pytest>=6; extra == 'dev'
Provides-Extra: docs
Requires-Dist: furo>=2023.08.17; extra == 'docs'
Requires-Dist: myst-parser>=0.13; extra == 'docs'
Requires-Dist: sphinx-autodoc-typehints; extra == 'docs'
Requires-Dist: sphinx-copybutton; extra == 'docs'
Requires-Dist: sphinx-inline-tabs; extra == 'docs'
Requires-Dist: sphinx>=7.0; extra == 'docs'
Requires-Dist: sphinxcontrib-mermaid; extra == 'docs'
Provides-Extra: test
Requires-Dist: pytest-cov>=3; extra == 'test'
Requires-Dist: pytest>=6; extra == 'test'
